cryp_to_go/__init__.py
cryp_to_go/cli.py
cryp_to_go/core.py
cryp_to_go/database.py
cryp_to_go/db_models.py
cryp_to_go/interface.py
cryp_to_go/path_handler.py
cryp_to_go-0.2.1.dist-info/LICENSE
cryp_to_go-0.2.1.dist-info/METADATA
cryp_to_go-0.2.1.dist-info/WHEEL
cryp_to_go-0.2.1.dist-info/entry_points.txt
cryp_to_go-0.2.1.dist-info/top_level.txt
cryp_to_go-0.2.1.dist-info/RECORD
