Metadata-Version: 2.1
Name: cryp-to-go
Version: 0.2.1
Summary: easy to use high-level crypto library for encrypted data storage/exchange
Home-page: https://github.com/matthiashuschle/cryp-to-go
Author: Matthias Huschle
Author-email: matthiashuschle@gmail.com
License: MIT
Platform: UNKNOWN
Requires-Python: >=3.6
Requires-Dist: pynacl (>=1.3.0)
Requires-Dist: cryptography (>=2.8)
Requires-Dist: peewee
